pytest_reqcov/__init__.py
pytest_reqcov/merge.py
pytest_reqcov/plugin.py
pytest_reqcov-0.2.0.dist-info/licenses/LICENSE
pytest_reqcov-0.2.0.dist-info/METADATA
pytest_reqcov-0.2.0.dist-info/WHEEL
pytest_reqcov-0.2.0.dist-info/entry_points.txt
pytest_reqcov-0.2.0.dist-info/top_level.txt
pytest_reqcov-0.2.0.dist-info/RECORD
